{
	"info": {
		"_postman_id": "6b16c32b-a279-4290-90fb-6f7b985c1387",
		"name": "Currency Coversation Service",
		"schema": "https://schema.getpostman.com/json/collection/v2.1.0/collection.json"
	},
	"item": [
		{
			"name": "Currency Coversation Service [USD -> INR] (server port : 8001)",
			"request": {
				"method": "GET",
				"header": [],
				"url": {
					"raw": "http://localhost:8100/currency-conversion/from/USD/to/INR/quantity/10",
					"protocol": "http",
					"host": [
						"localhost"
					],
					"port": "8100",
					"path": [
						"currency-conversion",
						"from",
						"USD",
						"to",
						"INR",
						"quantity",
						"10"
					]
				}
			},
			"response": []
		},
		{
			"name": "Currency Coversation Service [EUR-> INR] (server port : 8001)",
			"request": {
				"method": "GET",
				"header": [],
				"url": {
					"raw": "http://localhost:8100/currency-conversion/from/EUR/to/INR/quantity/10",
					"protocol": "http",
					"host": [
						"localhost"
					],
					"port": "8100",
					"path": [
						"currency-conversion",
						"from",
						"EUR",
						"to",
						"INR",
						"quantity",
						"10"
					]
				}
			},
			"response": []
		},
		{
			"name": "Currency Coversation Service [AUD-> INR] (server port : 8001)",
			"request": {
				"method": "GET",
				"header": [],
				"url": {
					"raw": "http://localhost:8100/currency-conversion/from/AUD/to/INR/quantity/10",
					"protocol": "http",
					"host": [
						"localhost"
					],
					"port": "8100",
					"path": [
						"currency-conversion",
						"from",
						"AUD",
						"to",
						"INR",
						"quantity",
						"10"
					]
				}
			},
			"response": []
		},
		{
			"name": "FEIGN Currency Coversation Service [AUD-> INR] (server port : 8001)",
			"request": {
				"method": "GET",
				"header": [],
				"url": {
					"raw": "http://localhost:8100/currency-conversion-feign/from/AUD/to/INR/quantity/20",
					"protocol": "http",
					"host": [
						"localhost"
					],
					"port": "8100",
					"path": [
						"currency-conversion-feign",
						"from",
						"AUD",
						"to",
						"INR",
						"quantity",
						"20"
					]
				}
			},
			"response": []
		},
		{
			"name": "FEIGN Currency Coversation Service [EUR-> INR] (server port : 8001)",
			"request": {
				"method": "GET",
				"header": [],
				"url": {
					"raw": "http://localhost:8100/currency-conversion-feign/from/EUR/to/INR/quantity/20",
					"protocol": "http",
					"host": [
						"localhost"
					],
					"port": "8100",
					"path": [
						"currency-conversion-feign",
						"from",
						"EUR",
						"to",
						"INR",
						"quantity",
						"20"
					]
				}
			},
			"response": []
		},
		{
			"name": "FEIGN Currency Coversation Service [USD-> INR] (server port : 8001)",
			"request": {
				"method": "GET",
				"header": [],
				"url": {
					"raw": "http://localhost:8100/currency-conversion-feign/from/USD/to/INR/quantity/20",
					"protocol": "http",
					"host": [
						"localhost"
					],
					"port": "8100",
					"path": [
						"currency-conversion-feign",
						"from",
						"USD",
						"to",
						"INR",
						"quantity",
						"20"
					]
				}
			},
			"response": []
		}
	]
}